agent_memory/__init__.py
agent_memory/consolidation.py
agent_memory/distillation.py
agent_memory/guardrails.py
agent_memory/injection.py
agent_memory/manager.py
agent_memory/state.py
agent_memory/storage/__init__.py
agent_memory/storage/base.py
agent_memory/storage/memory.py
agent_memory/storage/sqlite.py
agent_memory_state-0.1.0.dist-info/licenses/LICENSE
examples/travel_agent.py
agent_memory_state-0.1.0.dist-info/METADATA
agent_memory_state-0.1.0.dist-info/WHEEL
agent_memory_state-0.1.0.dist-info/top_level.txt
agent_memory_state-0.1.0.dist-info/RECORD
