Metadata-Version: 2.4
Name: agent-memory-state
Version: 0.1.0
Summary: Long-term memory management for AI agents
Author: Agent Memory Contributors
License: MIT
Project-URL: Homepage, https://github.com/your-org/agent-memory
Project-URL: Documentation, https://github.com/your-org/agent-memory#readme
Keywords: ai,agents,memory,llm,openai
Classifier: Development Status :: 3 - Alpha
Classifier: Intended Audience :: Developers
Classifier: License :: OSI Approved :: MIT License
Classifier: Programming Language :: Python :: 3
Classifier: Programming Language :: Python :: 3.9
Classifier: Programming Language :: Python :: 3.10
Classifier: Programming Language :: Python :: 3.11
Classifier: Programming Language :: Python :: 3.12
Classifier: Topic :: Scientific/Engineering :: Artificial Intelligence
Requires-Python: >=3.9
License-File: LICENSE
Requires-Dist: pyyaml>=6.0
Provides-Extra: openai
Requires-Dist: openai>=1.0.0; extra == "openai"
Provides-Extra: dev
Requires-Dist: pytest>=7.0.0; extra == "dev"
Requires-Dist: pytest-asyncio>=0.21.0; extra == "dev"
Requires-Dist: ruff>=0.1.0; extra == "dev"
Requires-Dist: mypy>=1.0.0; extra == "dev"
Provides-Extra: all
Requires-Dist: agent-memory[dev,openai]; extra == "all"
Dynamic: license-file
